.gitignore
CHANGES.txt
MANIFEST.in
README.rst
bootstrap.py
buildout.cfg
collective.baseline-configure.zcml
setup.py
collective/__init__.py
collective.baseline.egg-info/PKG-INFO
collective.baseline.egg-info/SOURCES.txt
collective.baseline.egg-info/dependency_links.txt
collective.baseline.egg-info/entry_points.txt
collective.baseline.egg-info/namespace_packages.txt
collective.baseline.egg-info/not-zip-safe
collective.baseline.egg-info/requires.txt
collective.baseline.egg-info/top_level.txt
collective/baseline/__init__.py
collective/baseline/configure.zcml
collective/baseline/layer.py
collective/baseline/rebuild_i18n.sh
collective/baseline/testing.py
collective/baseline/upgrades.py
collective/baseline/upgrades.zcml
collective/baseline/viewlet.pt
collective/baseline/viewlet.py
collective/baseline/locales/collective.baseline.pot
collective/baseline/locales/en/LC_MESSAGES/collective.baseline.po
collective/baseline/locales/fr/LC_MESSAGES/collective.baseline.po
collective/baseline/profiles/default/browserlayer.xml
collective/baseline/profiles/default/metadata.xml
collective/baseline/tests/__init__.py
collective/baseline/tests/base.py
collective/baseline/tests/test_setup.py