Metadata-Version: 1.0
Name: collective.baseline
Version: 1.0
Summary: Add a baseline to the header
Home-page: https://github.com/collective/collective.baseline
Author: JeanMichel FRANCOIS
Author-email: toutpt@gmail.com
License: GPL
Keywords: plone baseline
Platform: UNKNOWN
Classifier: Programming Language :: Python
Classifier: Framework :: Plone
Classifier: Framework :: Plone :: 4.0
Classifier: Framework :: Plone :: 4.1
Classifier: Framework :: Plone :: 4.2
